zaqar_tempest_plugin/__init__.py
zaqar_tempest_plugin/config.py
zaqar_tempest_plugin/plugin.py
zaqar_tempest_plugin/api_schema/__init__.py
zaqar_tempest_plugin/api_schema/response/__init__.py
zaqar_tempest_plugin/api_schema/response/v2/__init__.py
zaqar_tempest_plugin/api_schema/response/v2/queues.py
zaqar_tempest_plugin/services/__init__.py
zaqar_tempest_plugin/services/messaging/__init__.py
zaqar_tempest_plugin/services/messaging/json/__init__.py
zaqar_tempest_plugin/services/messaging/json/messaging_client.py
zaqar_tempest_plugin/tests/__init__.py
zaqar_tempest_plugin/tests/base.py
zaqar_tempest_plugin/tests/v2/__init__.py
zaqar_tempest_plugin/tests/v2/test_claims.py
zaqar_tempest_plugin/tests/v2/test_claims_negative.py
zaqar_tempest_plugin/tests/v2/test_messages.py
zaqar_tempest_plugin/tests/v2/test_messages_negative.py
zaqar_tempest_plugin/tests/v2/test_queues.py
zaqar_tempest_plugin/tests/v2/test_queues_negative.py
zaqar_tempest_plugin/tests/v2/test_subscriptions.py
zaqar_tempest_plugin/tests/v2/test_subscriptions_negative.py
zaqar_tempest_plugin-4.0.0.dist-info/AUTHORS
zaqar_tempest_plugin-4.0.0.dist-info/LICENSE
zaqar_tempest_plugin-4.0.0.dist-info/METADATA
zaqar_tempest_plugin-4.0.0.dist-info/WHEEL
zaqar_tempest_plugin-4.0.0.dist-info/entry_points.txt
zaqar_tempest_plugin-4.0.0.dist-info/pbr.json
zaqar_tempest_plugin-4.0.0.dist-info/top_level.txt
zaqar_tempest_plugin-4.0.0.dist-info/RECORD
